miax/__init__.py
miax/miax.py
miax-0.0.4.dist-info/METADATA
miax-0.0.4.dist-info/WHEEL
miax-0.0.4.dist-info/top_level.txt
miax-0.0.4.dist-info/RECORD
