Metadata-Version: 2.1
Name: miax
Version: 0.0.4
Summary: use it to make sure to have your values your useing are corect
Home-page: UNKNOWN
Author: fat.yellow.ducky
Author-email: <outlook_845155FE023A6EF8@outlook.com>
License: UNKNOWN
Keywords: geting,counting,words
Platform: UNKNOWN
Requires-Python: >=3.9.1
